odoo/addons/tracking_manager/README.rst
odoo/addons/tracking_manager/__init__.py
odoo/addons/tracking_manager/__manifest__.py
odoo/addons/tracking_manager/tools.py
odoo/addons/tracking_manager/i18n/es.po
odoo/addons/tracking_manager/i18n/fr.po
odoo/addons/tracking_manager/i18n/it.po
odoo/addons/tracking_manager/i18n/tracking_manager.pot
odoo/addons/tracking_manager/i18n/zh_CN.po
odoo/addons/tracking_manager/models/__init__.py
odoo/addons/tracking_manager/models/ir_model.py
odoo/addons/tracking_manager/models/ir_model_fields.py
odoo/addons/tracking_manager/models/mail_thread.py
odoo/addons/tracking_manager/models/mail_tracking_value.py
odoo/addons/tracking_manager/models/models.py
odoo/addons/tracking_manager/readme/CONTRIBUTORS.md
odoo/addons/tracking_manager/readme/DESCRIPTION.md
odoo/addons/tracking_manager/readme/USAGE.md
odoo/addons/tracking_manager/static/description/fields.png
odoo/addons/tracking_manager/static/description/icon.png
odoo/addons/tracking_manager/static/description/index.html
odoo/addons/tracking_manager/static/description/model_view.png
odoo/addons/tracking_manager/tests/__init__.py
odoo/addons/tracking_manager/tests/test_mail_tracking_value.py
odoo/addons/tracking_manager/tests/test_tracking_manager.py
odoo/addons/tracking_manager/views/ir_model.xml
odoo/addons/tracking_manager/views/ir_model_fields.xml
odoo/addons/tracking_manager/views/message_template.xml
odoo_addon_tracking_manager-18.0.1.1.0.dist-info/METADATA
odoo_addon_tracking_manager-18.0.1.1.0.dist-info/WHEEL
odoo_addon_tracking_manager-18.0.1.1.0.dist-info/top_level.txt
odoo_addon_tracking_manager-18.0.1.1.0.dist-info/RECORD
