Metadata-Version: 2.1
Name: odoo-addon-tracking_manager
Version: 18.0.1.1.0
Requires-Python: >=3.10
Requires-Dist: odoo==18.0.*
Summary: This module tracks all fields of a model, including one2many and many2many ones.
Home-page: https://github.com/OCA/server-tools
License: AGPL-3
Author: Akretion, Odoo Community Association (OCA)
Author-email: support@odoo-community.org
Classifier: Programming Language :: Python
Classifier: Framework :: Odoo
Classifier: Framework :: Odoo :: 18.0
Classifier: License :: OSI Approved :: GNU Affero General Public License v3
